{
  "version": "6.3.1",
  "flags": {},
  "shapes": [
    {
      "label": "Yellow Beans",
      "points": [
        [
          497.0,
          254.0
        ],
        [
          496.0,
          254.0
        ],
        [
          494.0,
          254.0
        ],
        [
          481.0,
          254.0
        ],
        [
          480.0,
          254.0
        ],
        [
          478.0,
          254.0
        ],
        [
          476.0,
          254.0
        ],
        [
          475.0,
          254.0
        ],
        [
          473.0,
          254.0
        ],
        [
          468.0,
          254.0
        ],
        [
          467.0,
          254.0
        ],
        [
          457.0,
          254.0
        ],
        [
          456.0,
          254.0
        ],
        [
          453.0,
          254.0
        ],
        [
          451.0,
          254.0
        ],
        [
          442.0,
          254.0
        ],
        [
          441.0,
          254.0
        ],
        [
          437.0,
          254.0
        ],
        [
          436.0,
          254.0
        ],
        [
          427.0,
          254.0
        ],
        [
          426.0,
          254.0
        ],
        [
          424.0,
          254.0
        ],
        [
          411.0,
          254.0
        ],
        [
          410.0,
          254.0
        ],
        [
          409.0,
          254.0
        ],
        [
          393.0,
          254.0
        ],
        [
          392.0,
          254.0
        ],
        [
          390.0,
          254.0
        ],
        [
          361.0,
          254.0
        ],
        [
          360.0,
          254.0
        ],
        [
          359.0,
          254.0
        ],
        [
          353.0,
          254.0
        ],
        [
          352.0,
          254.0
        ],
        [
          351.0,
          254.0
        ],
        [
          330.0,
          254.0
        ],
        [
          327.5,
          253.0
        ],
        [
          329.0,
          249.5
        ],
        [
          335.5,
          246.0
        ],
        [
          337.5,
          240.0
        ],
        [
          339.0,
          239.5
        ],
        [
          340.0,
          237.5
        ],
        [
          342.0,
          237.5
        ],
        [
          343.5,
          234.0
        ],
        [
          346.5,
          232.0
        ],
        [
          343.5,
          231.0
        ],
        [
          343.5,
          226.0
        ],
        [
          344.5,
          225.0
        ],
        [
          343.5,
          224.0
        ],
        [
          346.0,
          223.5
        ],
        [
          347.0,
          225.5
        ],
        [
          349.0,
          225.5
        ],
        [
          350.0,
          223.5
        ],
        [
          351.5,
          223.0
        ],
        [
          351.5,
          220.0
        ],
        [
          353.5,
          219.0
        ],
        [
          351.5,
          218.0
        ],
        [
          353.0,
          216.5
        ],
        [
          355.0,
          217.5
        ],
        [
          360.0,
          217.5
        ],
        [
          365.5,
          214.0
        ],
        [
          369.5,
          208.0
        ],
        [
          369.5,
          204.0
        ],
        [
          370.5,
          203.0
        ],
        [
          369.5,
          202.0
        ],
        [
          371.5,
          198.0
        ],
        [
          374.5,
          194.0
        ],
        [
          377.5,
          192.0
        ],
        [
          377.5,
          189.0
        ],
        [
          379.5,
          187.0
        ],
        [
          380.5,
          184.0
        ],
        [
          382.0,
          183.5
        ],
        [
          385.5,
          178.0
        ],
        [
          389.5,
          175.0
        ],
        [
          391.5,
          171.0
        ],
        [
          390.5,
          170.0
        ],
        [
          391.5,
          159.0
        ],
        [
          389.5,
          156.0
        ],
        [
          390.5,
          154.0
        ],
        [
          398.5,
          147.0
        ],
        [
          397.5,
          146.0
        ],
        [
          399.5,
          143.0
        ],
        [
          398.5,
          139.0
        ],
        [
          401.5,
          136.0
        ],
        [
          396.31012658227843,
          132.87974683544306
        ],
        [
          394.7278481012658,
          129.08227848101268
        ],
        [
          394.7278481012658,
          127.18354430379748
        ],
        [
          391.2468354430379,
          124.3354430379747
        ],
        [
          381.43670886075944,
          122.12025316455697
        ],
        [
          379.8544303797468,
          112.62658227848102
        ],
        [
          378.58860759493666,
          107.24683544303798
        ],
        [
          379.5379746835443,
          104.08227848101266
        ],
        [
          383.0189873417721,
          101.23417721518989
        ],
        [
          398.0,
          112.5
        ],
        [
          407.0,
          107.5
        ],
        [
          411.0,
          108.5
        ],
        [
          414.0,
          111.5
        ],
        [
          419.0,
          106.5
        ],
        [
          424.0,
          106.5
        ],
        [
          425.5,
          105.0
        ],
        [
          424.5,
          104.0
        ],
        [
          425.0,
          100.5
        ],
        [
          427.0,
          99.5
        ],
        [
          428.5,
          101.0
        ],
        [
          428.5,
          103.0
        ],
        [
          430.0,
          103.5
        ],
        [
          430.5,
          100.0
        ],
        [
          434.0,
          94.5
        ],
        [
          438.0,
          94.5
        ],
        [
          439.0,
          93.5
        ],
        [
          440.0,
          94.5
        ],
        [
          446.0,
          95.5
        ],
        [
          447.5,
          93.0
        ],
        [
          450.0,
          91.5
        ],
        [
          462.0,
          89.5
        ],
        [
          466.0,
          86.5
        ],
        [
          472.0,
          87.5
        ],
        [
          473.0,
          86.5
        ],
        [
          482.0,
          86.5
        ],
        [
          484.0,
          84.5
        ],
        [
          490.0,
          84.5
        ],
        [
          492.0,
          86.5
        ],
        [
          494.0,
          85.5
        ],
        [
          497.0,
          87.0
        ]
      ],
      "group_id": null,
      "description": "",
      "shape_type": "polygon",
      "flags": {},
      "mask": null
    },
    {
      "label": "Yellow Beans",
      "points": [
        [
          37.0,
          150.5
        ],
        [
          33.0,
          149.5
        ],
        [
          31.0,
          146.5
        ],
        [
          23.0,
          143.5
        ],
        [
          18.0,
          143.5
        ],
        [
          17.0,
          144.5
        ],
        [
          15.0,
          143.5
        ],
        [
          10.0,
          147.5
        ],
        [
          8.0,
          147.5
        ],
        [
          5.0,
          150.5
        ],
        [
          0.5,
          150.0
        ],
        [
          0.5,
          2.0
        ],
        [
          2.0,
          0.5
        ],
        [
          169.0,
          0.5
        ],
        [
          169.0,
          1.5
        ],
        [
          168.0,
          1.5
        ],
        [
          167.0,
          3.5
        ],
        [
          162.0,
          3.5
        ],
        [
          156.5,
          10.0
        ],
        [
          153.5,
          12.0
        ],
        [
          154.5,
          13.0
        ],
        [
          150.5,
          16.0
        ],
        [
          150.5,
          20.0
        ],
        [
          147.0,
          25.5
        ],
        [
          142.0,
          28.5
        ],
        [
          140.0,
          28.5
        ],
        [
          135.0,
          34.5
        ],
        [
          132.0,
          35.5
        ],
        [
          131.5,
          37.0
        ],
        [
          126.0,
          41.5
        ],
        [
          122.5,
          43.0
        ],
        [
          119.5,
          48.0
        ],
        [
          117.5,
          49.0
        ],
        [
          113.0,
          61.5
        ],
        [
          109.0,
          62.5
        ],
        [
          103.0,
          66.5
        ],
        [
          103.0,
          68.5
        ],
        [
          101.0,
          67.5
        ],
        [
          99.5,
          68.0
        ],
        [
          100.5,
          69.0
        ],
        [
          95.5,
          78.0
        ],
        [
          95.5,
          80.0
        ],
        [
          92.5,
          80.0
        ],
        [
          91.5,
          85.0
        ],
        [
          88.5,
          87.0
        ],
        [
          86.5,
          90.0
        ],
        [
          86.5,
          92.0
        ],
        [
          85.0,
          92.5
        ],
        [
          83.5,
          96.0
        ],
        [
          76.5,
          102.0
        ],
        [
          75.5,
          104.0
        ],
        [
          76.5,
          105.0
        ],
        [
          74.5,
          109.0
        ],
        [
          73.0,
          110.5
        ],
        [
          70.0,
          110.5
        ],
        [
          67.5,
          113.0
        ],
        [
          68.5,
          114.0
        ],
        [
          67.5,
          119.0
        ],
        [
          64.5,
          123.0
        ],
        [
          63.5,
          128.0
        ],
        [
          59.5,
          135.0
        ],
        [
          60.5,
          136.0
        ],
        [
          59.5,
          138.0
        ],
        [
          60.5,
          139.0
        ],
        [
          58.5,
          142.0
        ],
        [
          58.5,
          145.0
        ],
        [
          56.0,
          147.5
        ],
        [
          55.0,
          146.5
        ],
        [
          50.0,
          146.5
        ],
        [
          49.0,
          147.5
        ],
        [
          46.0,
          146.5
        ],
        [
          42.0,
          149.5
        ],
        [
          38.0,
          149.5
        ]
      ],
      "group_id": null,
      "description": "",
      "shape_type": "polygon",
      "flags": {},
      "mask": null
    },
    {
      "label": "Orange Beans",
      "points": [
        [
          132.0,
          254.0
        ],
        [
          1.0,
          254.0
        ],
        [
          0.5,
          154.0
        ],
        [
          6.0,
          150.5
        ],
        [
          8.0,
          150.5
        ],
        [
          11.0,
          147.5
        ],
        [
          15.0,
          145.5
        ],
        [
          18.0,
          145.5
        ],
        [
          19.0,
          144.5
        ],
        [
          20.0,
          145.5
        ],
        [
          27.0,
          145.5
        ],
        [
          29.5,
          148.0
        ],
        [
          29.5,
          150.0
        ],
        [
          32.0,
          152.5
        ],
        [
          35.0,
          153.5
        ],
        [
          39.981012658227854,
          149.96835443037975
        ],
        [
          49.47468354430381,
          147.4367088607595
        ],
        [
          55.80379746835444,
          147.75316455696205
        ],
        [
          60.867088607594944,
          153.13291139240508
        ],
        [
          55.80379746835444,
          162.31012658227849
        ],
        [
          62.0,
          167.5
        ],
        [
          63.5,
          170.0
        ],
        [
          75.0,
          180.5
        ],
        [
          78.0,
          180.5
        ],
        [
          81.0,
          178.5
        ],
        [
          85.0,
          178.5
        ],
        [
          86.5,
          181.0
        ],
        [
          86.5,
          183.0
        ],
        [
          88.5,
          185.0
        ],
        [
          90.5,
          189.0
        ],
        [
          90.5,
          191.0
        ],
        [
          93.5,
          197.0
        ],
        [
          93.5,
          211.0
        ],
        [
          94.5,
          212.0
        ],
        [
          94.5,
          214.0
        ],
        [
          96.5,
          216.0
        ],
        [
          97.5,
          219.0
        ],
        [
          101.5,
          221.0
        ],
        [
          102.5,
          223.0
        ],
        [
          102.5,
          229.0
        ],
        [
          107.5,
          231.0
        ],
        [
          108.5,
          235.0
        ],
        [
          109.5,
          236.0
        ],
        [
          109.5,
          239.0
        ],
        [
          111.5,
          241.0
        ],
        [
          109.5,
          244.0
        ],
        [
          109.5,
          247.0
        ],
        [
          111.0,
          248.5
        ],
        [
          119.0,
          249.5
        ],
        [
          122.0,
          251.5
        ],
        [
          126.0,
          249.5
        ],
        [
          129.0,
          249.5
        ],
        [
          132.0,
          252.0
        ],
        [
          132.0,
          254.0
        ]
      ],
      "group_id": null,
      "description": "",
      "shape_type": "polygon",
      "flags": {},
      "mask": null
    },
    {
      "label": "Black Beans",
      "points": [
        [
          398.3670886075949,
          117.5
        ],
        [
          396.8670886075949,
          117.0
        ],
        [
          397.8670886075949,
          114.0
        ],
        [
          393.8670886075949,
          106.0
        ],
        [
          388.8670886075949,
          105.0
        ],
        [
          392.3670886075949,
          104.5
        ],
        [
          393.8670886075949,
          101.0
        ],
        [
          391.3670886075949,
          99.5
        ],
        [
          388.3670886075949,
          100.5
        ],
        [
          386.8670886075949,
          98.0
        ],
        [
          388.8670886075949,
          97.0
        ],
        [
          388.3670886075949,
          95.5
        ],
        [
          385.3670886075949,
          95.5
        ],
        [
          375.3670886075949,
          90.5
        ],
        [
          371.8670886075949,
          81.0
        ],
        [
          368.8670886075949,
          79.0
        ],
        [
          368.3670886075949,
          76.5
        ],
        [
          363.3670886075949,
          77.5
        ],
        [
          358.3670886075949,
          75.5
        ],
        [
          356.3670886075949,
          72.5
        ],
        [
          354.3670886075949,
          72.5
        ],
        [
          350.8670886075949,
          69.0
        ],
        [
          351.8670886075949,
          68.0
        ],
        [
          351.3670886075949,
          60.5
        ],
        [
          342.3670886075949,
          62.5
        ],
        [
          341.3670886075949,
          64.5
        ],
        [
          336.3670886075949,
          62.5
        ],
        [
          334.8670886075949,
          61.0
        ],
        [
          335.3670886075949,
          59.5
        ],
        [
          332.8670886075949,
          60.0
        ],
        [
          333.8670886075949,
          59.0
        ],
        [
          332.8670886075949,
          58.0
        ],
        [
          337.8670886075949,
          53.0
        ],
        [
          336.8670886075949,
          52.0
        ],
        [
          339.3670886075949,
          51.5
        ],
        [
          340.3670886075949,
          49.5
        ],
        [
          343.3670886075949,
          49.5
        ],
        [
          343.8670886075949,
          48.0
        ],
        [
          336.3670886075949,
          48.5
        ],
        [
          334.3670886075949,
          46.5
        ],
        [
          331.3670886075949,
          47.5
        ],
        [
          327.3670886075949,
          45.5
        ],
        [
          325.8670886075949,
          39.0
        ],
        [
          321.3670886075949,
          38.5
        ],
        [
          318.8670886075949,
          35.0
        ],
        [
          318.8670886075949,
          30.0
        ],
        [
          320.3670886075949,
          28.5
        ],
        [
          313.3670886075949,
          30.5
        ],
        [
          307.8670886075949,
          27.0
        ],
        [
          308.8670886075949,
          26.0
        ],
        [
          307.8670886075949,
          23.0
        ],
        [
          310.8670886075949,
          21.0
        ],
        [
          309.8670886075949,
          20.0
        ],
        [
          314.8670886075949,
          17.0
        ],
        [
          311.3670886075949,
          16.5
        ],
        [
          310.8670886075949,
          13.0
        ],
        [
          307.8670886075949,
          12.0
        ],
        [
          306.8670886075949,
          10.0
        ],
        [
          308.3670886075949,
          5.5
        ],
        [
          304.3670886075949,
          9.5
        ],
        [
          303.3670886075949,
          8.5
        ],
        [
          293.1455696202531,
          0.0
        ],
        [
          296.3670886075949,
          9.5
        ],
        [
          294.3670886075949,
          12.5
        ],
        [
          292.3670886075949,
          13.5
        ],
        [
          290.3670886075949,
          12.5
        ],
        [
          291.3670886075949,
          14.5
        ],
        [
          288.3670886075949,
          13.5
        ],
        [
          286.3670886075949,
          14.5
        ],
        [
          284.8670886075949,
          13.0
        ],
        [
          287.3670886075949,
          12.5
        ],
        [
          288.8670886075949,
          10.0
        ],
        [
          285.3670886075949,
          5.5
        ],
        [
          281.3670886075949,
          7.5
        ],
        [
          277.8670886075949,
          6.0
        ],
        [
          279.3670886075949,
          4.5
        ],
        [
          277.3670886075949,
          5.5
        ],
        [
          274.3670886075949,
          2.5
        ],
        [
          270.3670886075949,
          4.5
        ],
        [
          265.8670886075949,
          2.0
        ],
        [
          291.3670886075949,
          0.5
        ],
        [
          299.15822784810126,
          6.297468354430391
        ],
        [
          293.8670886075949,
          5.0
        ],
        [
          295.8670886075949,
          7.0
        ],
        [
          295.3670886075949,
          8.5
        ],
        [
          298.3670886075949,
          7.5
        ],
        [
          286.1835443037974,
          0.6012658227848213
        ],
        [
          289.379746835443,
          0.0
        ],
        [
          300.10759493670884,
          0.0
        ],
        [
          294.0949367088607,
          0.28481012658228977
        ],
        [
          298.52531645569616,
          0.0
        ],
        [
          289.9810126582278,
          0.0
        ],
        [
          300.3670886075949,
          0.5
        ],
        [
          301.3670886075949,
          1.5
        ],
        [
          304.3670886075949,
          0.5
        ],
        [
          305.3670886075949,
          1.5
        ],
        [
          322.3670886075949,
          1.5
        ],
        [
          323.3670886075949,
          0.5
        ],
        [
          325.3670886075949,
          1.5
        ],
        [
          331.3670886075949,
          0.5
        ],
        [
          332.3670886075949,
          1.5
        ],
        [
          343.3670886075949,
          0.5
        ],
        [
          344.3670886075949,
          1.5
        ],
        [
          346.3670886075949,
          0.5
        ],
        [
          348.3670886075949,
          1.5
        ],
        [
          354.3670886075949,
          0.5
        ],
        [
          363.3670886075949,
          1.5
        ],
        [
          366.3670886075949,
          0.5
        ],
        [
          374.1582278481012,
          0.0
        ],
        [
          401.68987341772146,
          0.0
        ],
        [
          401.3670886075949,
          0.5
        ],
        [
          403.3670886075949,
          1.5
        ],
        [
          404.3670886075949,
          0.5
        ],
        [
          439.3670886075949,
          1.5
        ],
        [
          441.2961930852068,
          7.596454196607839e-65
        ],
        [
          443.3670886075949,
          1.5
        ],
        [
          444.3670886075949,
          0.5
        ],
        [
          453.2721518987341,
          0.0
        ],
        [
          449.7911392405063,
          0.0
        ],
        [
          445.99367088607585,
          0.0
        ],
        [
          443.4620253164556,
          0.0
        ],
        [
          455.48734177215186,
          0.0
        ],
        [
          451.05696202531635,
          0.0
        ],
        [
          451.8670886075949,
          2.0
        ],
        [
          455.3670886075949,
          0.5
        ],
        [
          478.3670886075949,
          1.5
        ],
        [
          480.8670886075949,
          3.0
        ],
        [
          479.3670886075949,
          5.5
        ],
        [
          476.8670886075949,
          4.0
        ],
        [
          477.3670886075949,
          2.5
        ],
        [
          474.8670886075949,
          4.0
        ],
        [
          477.8670886075949,
          6.0
        ],
        [
          477.3670886075949,
          7.5
        ],
        [
          483.8670886075949,
          4.0
        ],
        [
          481.3670886075949,
          1.5
        ],
        [
          483.3670886075949,
          2.5
        ],
        [
          486.3670886075949,
          0.5
        ],
        [
          491.3670886075949,
          0.5
        ],
        [
          497.3670886075949,
          0.0
        ],
        [
          496.3670886075949,
          1.5
        ],
        [
          497.3670886075949,
          0.0
        ],
        [
          496.3670886075949,
          6.0
        ],
        [
          496.3670886075949,
          13.0
        ],
        [
          496.3670886075949,
          20.0
        ],
        [
          494.3670886075949,
          19.5
        ],
        [
          495.8670886075949,
          18.0
        ],
        [
          493.3670886075949,
          16.5
        ],
        [
          497.3670886075949,
          16.424050632911403
        ],
        [
          497.3670886075949,
          17.373417721518997
        ],
        [
          497.3670886075949,
          19.588607594936718
        ],
        [
          491.3670886075949,
          21.5
        ],
        [
          497.3670886075949,
          19.588607594936718
        ],
        [
          497.3670886075949,
          22.436708860759502
        ],
        [
          497.3670886075949,
          24.01898734177216
        ],
        [
          497.3670886075949,
          24.33544303797469
        ],
        [
          497.3670886075949,
          22.436708860759502
        ],
        [
          497.3670886075949,
          24.01898734177216
        ],
        [
          497.3670886075949,
          19.588607594936718
        ],
        [
          497.3670886075949,
          21.80379746835444
        ],
        [
          497.3670886075949,
          23.386075949367097
        ],
        [
          490.8670886075949,
          24.0
        ],
        [
          497.3670886075949,
          24.651898734177223
        ],
        [
          497.3670886075949,
          26.23417721518988
        ],
        [
          492.8670886075949,
          30.0
        ],
        [
          497.3670886075949,
          31.93037974683545
        ],
        [
          493.8670886075949,
          34.0
        ],
        [
          497.3670886075949,
          36.04430379746836
        ],
        [
          496.3670886075949,
          40.0
        ],
        [
          494.8670886075949,
          42.0
        ],
        [
          495.8670886075949,
          43.0
        ],
        [
          497.3670886075949,
          47.753164556962034
        ],
        [
          497.3670886075949,
          52.81645569620254
        ],
        [
          493.8670886075949,
          59.0
        ],
        [
          497.3670886075949,
          60.4113924050633
        ],
        [
          497.3670886075949,
          66.4240506329114
        ],
        [
          497.3670886075949,
          68.95569620253166
        ],
        [
          497.3670886075949,
          72.12025316455697
        ],
        [
          497.3670886075949,
          74.96835443037976
        ],
        [
          496.3670886075949,
          74.0
        ],
        [
          496.3670886075949,
          76.0
        ],
        [
          494.8670886075949,
          77.0
        ],
        [
          497.3670886075949,
          81.29746835443039
        ],
        [
          493.8670886075949,
          86.0
        ],
        [
          484.3670886075949,
          85.5
        ],
        [
          484.8670886075949,
          89.0
        ],
        [
          483.8670886075949,
          92.0
        ],
        [
          482.3670886075949,
          92.5
        ],
        [
          481.8670886075949,
          88.0
        ],
        [
          483.8670886075949,
          84.0
        ],
        [
          481.8670886075949,
          82.0
        ],
        [
          485.8670886075949,
          80.0
        ],
        [
          480.8037974683544,
          86.04430379746837
        ],
        [
          480.8037974683544,
          86.04430379746837
        ],
        [
          477.6392405063291,
          85.41139240506331
        ],
        [
          475.10759493670884,
          86.3607594936709
        ],
        [
          472.5759493670886,
          86.3607594936709
        ],
        [
          471.62658227848095,
          84.77848101265825
        ],
        [
          475.3670886075949,
          77.5
        ],
        [
          471.31012658227843,
          85.72784810126583
        ],
        [
          469.7278481012658,
          86.3607594936709
        ],
        [
          470.8670886075949,
          78.0
        ],
        [
          471.8670886075949,
          85.0
        ],
        [
          470.3670886075949,
          86.5
        ],
        [
          461.3670886075949,
          87.5
        ],
        [
          459.8670886075949,
          85.0
        ],
        [
          460.55063291139237,
          85.72784810126583
        ],
        [
          460.3670886075949,
          83.5
        ],
        [
          459.3670886075949,
          80.5
        ],
        [
          460.23417721518985,
          87.62658227848102
        ],
        [
          457.3670886075949,
          89.5
        ],
        [
          446.3670886075949,
          90.5
        ],
        [
          443.3670886075949,
          94.5
        ],
        [
          440.3670886075949,
          95.5
        ],
        [
          436.3670886075949,
          94.5
        ],
        [
          434.3670886075949,
          89.5
        ],
        [
          431.3670886075949,
          90.5
        ],
        [
          430.8670886075949,
          92.0
        ],
        [
          433.8670886075949,
          93.0
        ],
        [
          424.3670886075949,
          95.5
        ],
        [
          424.8670886075949,
          101.0
        ],
        [
          419.3670886075949,
          106.5
        ],
        [
          414.3670886075949,
          107.5
        ],
        [
          410.3670886075949,
          105.5
        ],
        [
          404.3670886075949,
          106.5
        ],
        [
          404.3670886075949,
          103.5
        ],
        [
          411.3670886075949,
          104.5
        ],
        [
          412.8670886075949,
          103.0
        ],
        [
          411.3670886075949,
          101.5
        ],
        [
          405.3670886075949,
          102.5
        ],
        [
          404.8670886075949,
          100.0
        ],
        [
          407.8670886075949,
          99.0
        ],
        [
          405.3670886075949,
          97.5
        ],
        [
          402.8670886075949,
          100.0
        ],
        [
          402.8670886075949,
          108.0
        ],
        [
          404.8670886075949,
          109.0
        ],
        [
          400.8670886075949,
          111.0
        ],
        [
          400.8670886075949,
          114.0
        ]
      ],
      "group_id": null,
      "description": "",
      "shape_type": "polygon",
      "flags": {},
      "mask": null
    },
    {
      "label": "Green Beans",
      "points": [
        [
          252.0,
          254.0
        ],
        [
          135.0,
          254.0
        ],
        [
          129.0,
          247.5
        ],
        [
          117.0,
          247.5
        ],
        [
          118.5,
          246.0
        ],
        [
          116.5,
          245.0
        ],
        [
          116.5,
          237.0
        ],
        [
          113.0,
          238.5
        ],
        [
          109.5,
          235.0
        ],
        [
          108.5,
          226.0
        ],
        [
          106.5,
          226.0
        ],
        [
          106.5,
          223.0
        ],
        [
          102.5,
          221.0
        ],
        [
          100.5,
          215.0
        ],
        [
          95.5,
          211.0
        ],
        [
          97.5,
          198.0
        ],
        [
          88.5,
          178.0
        ],
        [
          85.0,
          173.5
        ],
        [
          79.0,
          171.5
        ],
        [
          77.0,
          167.5
        ],
        [
          70.0,
          167.5
        ],
        [
          72.5,
          166.0
        ],
        [
          69.5,
          164.0
        ],
        [
          70.0,
          161.5
        ],
        [
          68.0,
          166.5
        ],
        [
          67.0,
          163.5
        ],
        [
          58.5,
          162.0
        ],
        [
          60.0,
          159.5
        ],
        [
          69.5,
          160.0
        ],
        [
          69.0,
          156.5
        ],
        [
          65.0,
          158.5
        ],
        [
          62.5,
          155.0
        ],
        [
          62.5,
          135.0
        ],
        [
          63.5,
          129.0
        ],
        [
          70.5,
          122.0
        ],
        [
          72.5,
          117.0
        ],
        [
          70.5,
          115.0
        ],
        [
          71.5,
          112.0
        ],
        [
          77.5,
          110.0
        ],
        [
          78.5,
          104.0
        ],
        [
          96.5,
          81.0
        ],
        [
          99.5,
          71.0
        ],
        [
          113.0,
          63.5
        ],
        [
          121.5,
          47.0
        ],
        [
          132.0,
          38.5
        ],
        [
          136.0,
          37.5
        ],
        [
          140.0,
          30.5
        ],
        [
          150.5,
          25.0
        ],
        [
          152.5,
          15.0
        ],
        [
          155.0,
          12.5
        ],
        [
          157.5,
          13.0
        ],
        [
          161.0,
          2.5
        ],
        [
          165.0,
          3.5
        ],
        [
          170.0,
          0.5
        ],
        [
          293.0,
          0.5
        ],
        [
          295.0,
          2.5
        ],
        [
          306.0,
          0.5
        ],
        [
          311.0,
          3.5
        ],
        [
          317.0,
          2.5
        ],
        [
          317.0,
          4.5
        ],
        [
          314.5,
          4.0
        ],
        [
          318.5,
          8.0
        ],
        [
          317.5,
          16.0
        ],
        [
          312.5,
          17.0
        ],
        [
          317.5,
          19.0
        ],
        [
          317.5,
          23.0
        ],
        [
          320.5,
          24.0
        ],
        [
          321.5,
          28.0
        ],
        [
          318.5,
          29.0
        ],
        [
          316.5,
          36.0
        ],
        [
          321.0,
          35.5
        ],
        [
          324.5,
          39.0
        ],
        [
          326.0,
          48.5
        ],
        [
          332.0,
          47.5
        ],
        [
          335.5,
          50.0
        ],
        [
          336.5,
          52.0
        ],
        [
          332.5,
          56.0
        ],
        [
          336.5,
          60.0
        ],
        [
          333.5,
          62.0
        ],
        [
          337.5,
          63.0
        ],
        [
          338.71518987341767,
          64.84177215189875
        ],
        [
          338.39873417721515,
          64.84177215189875
        ],
        [
          339.9810126582278,
          61.993670886075954
        ],
        [
          340.29746835443035,
          63.57594936708862
        ],
        [
          341.56329113924045,
          65.47468354430382
        ],
        [
          348.52531645569616,
          62.31012658227849
        ],
        [
          351.37341772151893,
          68.95569620253166
        ],
        [
          351.0569620253164,
          70.22151898734178
        ],
        [
          353.27215189873414,
          70.53797468354432
        ],
        [
          352.6392405063291,
          69.58860759493672
        ],
        [
          353.0,
          73.5
        ],
        [
          352.5,
          76.0
        ],
        [
          355.8037974683544,
          73.3860759493671
        ],
        [
          357.7025316455696,
          75.60126582278482
        ],
        [
          360.23417721518985,
          75.28481012658229
        ],
        [
          360.8670886075949,
          76.86708860759495
        ],
        [
          363.0,
          77.5
        ],
        [
          371.5,
          83.0
        ],
        [
          373.5,
          89.0
        ],
        [
          370.5,
          93.0
        ],
        [
          373.20886075949363,
          94.90506329113926
        ],
        [
          382.38607594936707,
          97.43670886075951
        ],
        [
          374.0,
          95.5
        ],
        [
          383.5,
          98.0
        ],
        [
          377.0,
          105.5
        ],
        [
          373.5,
          106.0
        ],
        [
          372.5,
          113.0
        ],
        [
          375.0,
          108.5
        ],
        [
          378.0,
          108.5
        ],
        [
          375.5,
          111.0
        ],
        [
          378.5,
          115.0
        ],
        [
          378.5,
          121.0
        ],
        [
          381.0,
          124.5
        ],
        [
          385.5,
          125.0
        ],
        [
          381.5,
          127.0
        ],
        [
          390.0,
          127.5
        ],
        [
          392.5,
          132.0
        ],
        [
          392.5,
          134.0
        ],
        [
          389.5,
          135.0
        ],
        [
          392.5,
          137.0
        ],
        [
          389.5,
          139.0
        ],
        [
          397.5759493670886,
          142.68987341772154
        ],
        [
          394.4113924050633,
          146.48734177215192
        ],
        [
          389.5,
          151.0
        ],
        [
          384.5,
          155.0
        ],
        [
          384.5,
          159.0
        ],
        [
          387.5,
          161.0
        ],
        [
          384.5,
          167.0
        ],
        [
          385.5,
          170.0
        ],
        [
          385.8670886075949,
          172.12025316455697
        ],
        [
          385.23417721518985,
          175.91772151898735
        ],
        [
          381.43670886075944,
          178.13291139240508
        ],
        [
          380.5,
          178.0
        ],
        [
          380.17088607594934,
          180.98101265822785
        ],
        [
          380.17088607594934,
          182.87974683544306
        ],
        [
          380.8037974683544,
          180.3481012658228
        ],
        [
          390.29746835443035,
          157.87974683544306
        ],
        [
          386.8164556962025,
          154.3987341772152
        ],
        [
          389.3481012658228,
          156.93037974683546
        ],
        [
          389.3481012658228,
          161.36075949367088
        ],
        [
          389.6645569620253,
          155.3481012658228
        ],
        [
          389.9810126582278,
          154.3987341772152
        ],
        [
          391.56329113924045,
          159.4620253164557
        ],
        [
          389.6645569620253,
          160.72784810126583
        ],
        [
          390.9303797468354,
          163.5759493670886
        ],
        [
          391.87974683544303,
          170.85443037974684
        ],
        [
          388.71518987341767,
          173.70253164556962
        ],
        [
          385.55063291139237,
          176.86708860759495
        ],
        [
          382.38607594936707,
          183.19620253164558
        ],
        [
          377.6392405063291,
          188.2594936708861
        ],
        [
          377.9556962025316,
          191.4240506329114
        ],
        [
          375.10759493670884,
          193.63924050632912
        ],
        [
          371.62658227848095,
          197.4367088607595
        ],
        [
          370.6772151898734,
          201.86708860759495
        ],
        [
          369.4113924050633,
          207.24683544303798
        ],
        [
          365.29746835443035,
          212.94303797468356
        ],
        [
          360.55063291139237,
          217.05696202531647
        ],
        [
          351.68987341772146,
          214.84177215189874
        ],
        [
          349.7911392405063,
          219.90506329113924
        ],
        [
          348.20886075949363,
          225.60126582278482
        ],
        [
          346.31012658227843,
          222.4367088607595
        ],
        [
          343.1455696202531,
          224.65189873417722
        ],
        [
          341.2468354430379,
          230.66455696202533
        ],
        [
          343.46202531645565,
          235.72784810126583
        ],
        [
          339.3481012658228,
          239.2088607594937
        ],
        [
          337.4493670886076,
          241.74050632911394
        ],
        [
          335.23417721518985,
          246.4873417721519
        ],
        [
          329.22151898734177,
          249.65189873417722
        ],
        [
          323.5,
          254.0
        ],
        [
          321.0,
          254.0
        ],
        [
          317.0,
          250.5
        ],
        [
          317.0,
          254.0
        ]
      ],
      "group_id": null,
      "description": "",
      "shape_type": "polygon",
      "flags": {},
      "mask": null
    }
  ],
  "imagePath": "Img06.jpg",
  "imageData": null,
  "imageHeight": 255,
  "imageWidth": 498
}